{
  "best_metric": 1.1332600116729736,
  "best_model_checkpoint": "MusicBot-ft-2\\checkpoint-25",
  "epoch": 1.0,
  "eval_steps": 500,
  "global_step": 25,
  "is_hyper_param_search": false,
  "is_local_process_zero": true,
  "is_world_process_zero": true,
  "log_history": [
    {
      "epoch": 1.0,
      "grad_norm": 1.1050245761871338,
      "learning_rate": 0.00016260162601626016,
      "loss": 2.7292,
      "step": 25
    },
    {
      "epoch": 1.0,
      "eval_loss": 1.1332600116729736,
      "eval_runtime": 19.1218,
      "eval_samples_per_second": 20.919,
      "eval_steps_per_second": 0.68,
      "step": 25
    }
  ],
  "logging_steps": 500,
  "max_steps": 125,
  "num_input_tokens_seen": 0,
  "num_train_epochs": 5,
  "save_steps": 500,
  "total_flos": 348298397614080.0,
  "train_batch_size": 32,
  "trial_name": null,
  "trial_params": null
}
